ai/__init__.py
ai/__init__.pyi
ai/assets/__init__.py
ai/assets/__init__.pyi
ai/assets/prompts/__init__.py
ai/assets/prompts/__init__.pyi
ai/assets/prompts/commit.md
ai/assets/prompts/description-long.md
ai/assets/prompts/description.md
ai/assets/prompts/topics.md
ai/cmd/__init__.py
ai/cmd/__init__.pyi
ai/cmd/_app.py
ai/cmd/commit/__init__.py
ai/cmd/commit/__init__.pyi
ai/cmd/commit/_app.py
ai/cmd/commit/_main.py
ai/cmd/repo/__init__.py
ai/cmd/repo/__init__.pyi
ai/cmd/repo/_app.py
ai/cmd/repo/_main.py
ai/cmd/repo/description/__init__.py
ai/cmd/repo/description/__init__.pyi
ai/cmd/repo/description/_app.py
ai/cmd/repo/description/_main.py
ai/cmd/repo/topics/__init__.py
ai/cmd/repo/topics/__init__.pyi
ai/cmd/repo/topics/_app.py
ai/cmd/repo/topics/_main.py
ai/config/__init__.py
ai/config/__init__.pyi
ai/config/_config.py
ai/config/_get_config.py
ai/config/_init_litellm.py
ai/config/_router_config.py
ai/interactive/__init__.py
ai/interactive/__init__.pyi
ai/interactive/_output.py
ai/interactive/_usage.py
ai/logging/__init__.py
ai/logging/__init__.pyi
ai/logging/_fix_litellm.py
ai/logging/_init.py
ai/logging/_loguru.py
ai/utils/__init__.py
ai/utils/__init__.pyi
ai/utils/_add_command.py
ai/utils/_as_list.py
ai/utils/_extract_between_tags.py
ai/utils/_get_app_dir.py
ai/utils/_get_config.py
ai/utils/_get_prompt.py
ai/utils/_ignore.py
ai/utils/_repomix.py
ai/utils/_run.py
ai/utils/_working_dir.py
ai/utils/git/__init__.py
ai/utils/git/__init__.pyi
ai/utils/git/_root.py
liblaf_ai_cli-0.0.2.dist-info/METADATA
liblaf_ai_cli-0.0.2.dist-info/WHEEL
liblaf_ai_cli-0.0.2.dist-info/entry_points.txt
liblaf_ai_cli-0.0.2.dist-info/licenses/LICENSE
liblaf_ai_cli-0.0.2.dist-info/RECORD
