Metadata-Version: 2.3
Name: liblaf-ai-cli
Version: 0.0.2
Summary: 🚀 AI CLI - A powerful and versatile command-line interface for AI-driven code commit messages, repository descriptions, and topic generation, designed to enhance productivity and collaboration.
Project-URL: Changelog, https://github.com/liblaf/ai-cli/blob/main/CHANGELOG.md
Project-URL: Homepage, https://github.com/liblaf/ai-cli
Project-URL: Issue Tracker, https://github.com/liblaf/ai-cli/issues
Project-URL: Release Notes, https://github.com/liblaf/ai-cli/releases
Project-URL: Source Code, https://github.com/liblaf/ai-cli
Author-email: liblaf <30631553+liblaf@users.noreply.github.com>
Requires-Python: >=3.12
Requires-Dist: gitpython>=3.1.43
Requires-Dist: hishel>=0.1.1
Requires-Dist: httpx[socks]>=0.27.2
Requires-Dist: lazy-loader>=0.4
Requires-Dist: litellm>=1.52.12
Requires-Dist: loguru>=0.7.2
Requires-Dist: pydantic-settings>=2.6.1
Requires-Dist: pydantic>=2.10.1
Requires-Dist: python-dotenv>=1.0.1
Requires-Dist: rich>=13.9.4
Requires-Dist: transformers>=4.46.3
Requires-Dist: typer-di>=0.1.2
Requires-Dist: typer>=0.13.1
